[
 {
  "nb": 32,
  "nval": 16,
  "ncond": 16,
  "b_start": 10,
  "b_end": 42,
  "rank": 4568,
  "n_guard": 8,
  "ortho": 0.08222,
  "fH_R_GiB": 44.77491760253906,
  "t_galerkin": 19.513431549072266,
  "status": "ok",
  "DFT_gate_meV": 60.54486268747074,
  "DFT_min_sval": 0.9539299160067263,
  "DFT_recon_meV": 60.54486268747074,
  "DFT_d2_meV": 2593.2492689032374,
  "DFT_passed": false,
  "DFT_refused": false,
  "DFT_t_grid": 69.26761603355408,
  "DFT_t_path": 0.0,
  "DFT_status": "ok",
  "QP_gate_meV": 58.00332272412119,
  "QP_min_sval": 0.9542323776330986,
  "QP_recon_meV": 48.823858107997204,
  "QP_d2_meV": 3208.505569474815,
  "QP_passed": false,
  "QP_refused": false,
  "QP_t_grid": 66.4322898387909,
  "QP_t_path": 0.0,
  "QP_status": "ok"
 },
 {
  "nb": 36,
  "nval": 18,
  "ncond": 18,
  "b_start": 8,
  "b_end": 44,
  "rank": 4716,
  "n_guard": 10,
  "ortho": 0.2308,
  "fH_R_GiB": 47.723270416259766,
  "t_galerkin": 23.18198037147522,
  "status": "ok",
  "DFT_gate_meV": 817.814,
  "DFT_min_sval": 0.944,
  "DFT_recon_meV": 817.8140948972493,
  "DFT_d2_meV": 1890.097228520657,
  "DFT_passed": false,
  "DFT_refused": true,
  "DFT_t_grid": 76.3803162574768,
  "DFT_t_path": 0.0,
  "DFT_status": "ok",
  "QP_gate_meV": 675.1648609103916,
  "QP_min_sval": 0.9551276066158451,
  "QP_recon_meV": 674.9628609103913,
  "QP_d2_meV": 1539.373721497432,
  "QP_passed": false,
  "QP_refused": false,
  "QP_t_grid": 72.48538827896118,
  "QP_t_path": 0.0,
  "QP_status": "ok"
 },
 {
  "nb": 40,
  "nval": 20,
  "ncond": 20,
  "b_start": 6,
  "b_end": 46,
  "rank": 4804,
  "n_guard": 12,
  "ortho": 0.451,
  "fH_R_GiB": 49.52090835571289,
  "t_galerkin": 21.539555311203003,
  "status": "ok",
  "DFT_gate_meV": 1314.105,
  "DFT_min_sval": 0.8574,
  "DFT_recon_meV": 1314.1053618838382,
  "DFT_d2_meV": 1298.9587795143225,
  "DFT_passed": false,
  "DFT_refused": true,
  "DFT_t_grid": 76.21908402442932,
  "DFT_t_path": 0.0,
  "DFT_status": "ok",
  "QP_gate_meV": 926.068,
  "QP_min_sval": 0.9172,
  "QP_recon_meV": 925.727113791406,
  "QP_d2_meV": 1631.1998308089073,
  "QP_passed": false,
  "QP_refused": true,
  "QP_t_grid": 75.22621488571167,
  "QP_t_path": 0.0,
  "QP_status": "ok"
 }
]