{
  "peak_bytes": 0,
  "peak_sample": null,
  "timeline": [
    {
      "t": 2.330925118178129,
      "bytes_in_use": 0,
      "peak_bytes_in_use": 0,
      "live_bytes_sum": 0,
      "n_live_arrays": 0,
      "top_arrays": []
    },
    {
      "t": 2.586118150036782,
      "bytes_in_use": 0,
      "peak_bytes_in_use": 0,
      "live_bytes_sum": 0,
      "n_live_arrays": 0,
      "top_arrays": []
    },
    {
      "t": 2.8368745232000947,
      "bytes_in_use": 0,
      "peak_bytes_in_use": 0,
      "live_bytes_sum": 0,
      "n_live_arrays": 0,
      "top_arrays": []
    },
    {
      "t": 3.087762301089242,
      "bytes_in_use": 0,
      "peak_bytes_in_use": 0,
      "live_bytes_sum": 0,
      "n_live_arrays": 0,
      "top_arrays": []
    },
    {
      "t": 3.3379410880152136,
      "bytes_in_use": 0,
      "peak_bytes_in_use": 0,
      "live_bytes_sum": 8,
      "n_live_arrays": 1,
      "top_arrays": [
        {
          "bytes": 8,
          "dtype": "float64",
          "shape": []
        }
      ]
    },
    {
      "t": 3.588201512116939,
      "bytes_in_use": 0,
      "peak_bytes_in_use": 0,
      "live_bytes_sum": 192,
      "n_live_arrays": 3,
      "top_arrays": [
        {
          "bytes": 128,
          "dtype": "float64",
          "shape": [
            4,
            2,
            2
          ]
        },
        {
          "bytes": 32,
          "dtype": "float64",
          "shape": [
            2,
            2
          ]
        },
        {
          "bytes": 32,
          "dtype": "float64",
          "shape": [
            2,
            2
          ]
        }
      ]
    },
    {
      "t": 3.838438511127606,
      "bytes_in_use": 0,
      "peak_bytes_in_use": 0,
      "live_bytes_sum": 192,
      "n_live_arrays": 3,
      "top_arrays": [
        {
          "bytes": 128,
          "dtype": "float64",
          "shape": [
            4,
            2,
            2
          ]
        },
        {
          "bytes": 32,
          "dtype": "float64",
          "shape": [
            2,
            2
          ]
        },
        {
          "bytes": 32,
          "dtype": "float64",
          "shape": [
            2,
            2
          ]
        }
      ]
    },
    {
      "t": 4.088614462176338,
      "bytes_in_use": 0,
      "peak_bytes_in_use": 0,
      "live_bytes_sum": 192,
      "n_live_arrays": 3,
      "top_arrays": [
        {
          "bytes": 128,
          "dtype": "float64",
          "shape": [
            4,
            2,
            2
          ]
        },
        {
          "bytes": 32,
          "dtype": "float64",
          "shape": [
            2,
            2
          ]
        },
        {
          "bytes": 32,
          "dtype": "float64",
          "shape": [
            2,
            2
          ]
        }
      ]
    },
    {
      "t": 4.339083339087665,
      "bytes_in_use": 0,
      "peak_bytes_in_use": 0,
      "live_bytes_sum": 24,
      "n_live_arrays": 2,
      "top_arrays": [
        {
          "bytes": 16,
          "dtype": "float64",
          "shape": [
            2
          ]
        },
        {
          "bytes": 8,
          "dtype": "float64",
          "shape": []
        }
      ]
    },
    {
      "t": 4.589280792046338,
      "bytes_in_use": 0,
      "peak_bytes_in_use": 0,
      "live_bytes_sum": 24,
      "n_live_arrays": 2,
      "top_arrays": [
        {
          "bytes": 16,
          "dtype": "float64",
          "shape": [
            2
          ]
        },
        {
          "bytes": 8,
          "dtype": "float64",
          "shape": []
        }
      ]
    },
    {
      "t": 5.3655644280370325,
      "bytes_in_use": 0,
      "peak_bytes_in_use": 0,
      "live_bytes_sum": 0,
      "n_live_arrays": 0,
      "top_arrays": []
    },
    {
      "t": 5.616960789076984,
      "bytes_in_use": 0,
      "peak_bytes_in_use": 0,
      "live_bytes_sum": 235937304,
      "n_live_arrays": 4,
      "top_arrays": [
        {
          "bytes": 235929600,
          "dtype": "complex128",
          "shape": [
            1,
            1,
            1,
            4,
            4,
            4,
            480,
            480
          ]
        },
        {
          "bytes": 7680,
          "dtype": "complex128",
          "shape": [
            480
          ]
        },
        {
          "bytes": 12,
          "dtype": "int32",
          "shape": [
            3
          ]
        },
        {
          "bytes": 12,
          "dtype": "int32",
          "shape": [
            3
          ]
        }
      ]
    },
    {
      "t": 5.867250349139795,
      "bytes_in_use": 0,
      "peak_bytes_in_use": 0,
      "live_bytes_sum": 412915224,
      "n_live_arrays": 8,
      "top_arrays": [
        {
          "bytes": 235929600,
          "dtype": "complex128",
          "shape": [
            1,
            1,
            1,
            4,
            4,
            4,
            480,
            480
          ]
        },
        {
          "bytes": 58982400,
          "dtype": "complex128",
          "shape": [
            64,
            60,
            2,
            480
          ]
        },
        {
          "bytes": 58982400,
          "dtype": "complex128",
          "shape": [
            64,
            60,
            2,
            480
          ]
        },
        {
          "bytes": 58982400,
          "dtype": "complex128",
          "shape": [
            64,
            60,
            2,
            480
          ]
        },
        {
          "bytes": 30720,
          "dtype": "float64",
          "shape": [
            64,
            60
          ]
        },
        {
          "bytes": 7680,
          "dtype": "complex128",
          "shape": [
            480
          ]
        },
        {
          "bytes": 12,
          "dtype": "int32",
          "shape": [
            3
          ]
        },
        {
          "bytes": 12,
          "dtype": "int32",
          "shape": [
            3
          ]
        }
      ]
    },
    {
      "t": 6.117531183175743,
      "bytes_in_use": 0,
      "peak_bytes_in_use": 0,
      "live_bytes_sum": 530880024,
      "n_live_arrays": 10,
      "top_arrays": [
        {
          "bytes": 235929600,
          "dtype": "complex128",
          "shape": [
            1,
            1,
            1,
            4,
            4,
            4,
            480,
            480
          ]
        },
        {
          "bytes": 58982400,
          "dtype": "complex128",
          "shape": [
            64,
            480,
            60,
            2
          ]
        },
        {
          "bytes": 58982400,
          "dtype": "complex128",
          "shape": [
            64,
            480,
            60,
            2
          ]
        },
        {
          "bytes": 58982400,
          "dtype": "complex128",
          "shape": [
            64,
            60,
            2,
            480
          ]
        },
        {
          "bytes": 58982400,
          "dtype": "complex128",
          "shape": [
            64,
            2,
            480,
            60
          ]
        },
        {
          "bytes": 58982400,
          "dtype": "complex128",
          "shape": [
            64,
            2,
            480,
            60
          ]
        },
        {
          "bytes": 30720,
          "dtype": "float64",
          "shape": [
            64,
            60
          ]
        },
        {
          "bytes": 7680,
          "dtype": "complex128",
          "shape": [
            480
          ]
        },
        {
          "bytes": 12,
          "dtype": "int32",
          "shape": [
            3
          ]
        },
        {
          "bytes": 12,
          "dtype": "int32",
          "shape": [
            3
          ]
        }
      ]
    },
    {
      "t": 6.367820874089375,
      "bytes_in_use": 0,
      "peak_bytes_in_use": 0,
      "live_bytes_sum": 707885084,
      "n_live_arrays": 13,
      "top_arrays": [
        {
          "bytes": 235929600,
          "dtype": "complex128",
          "shape": [
            64,
            480,
            480
          ]
        },
        {
          "bytes": 235929600,
          "dtype": "complex128",
          "shape": [
            1,
            1,
            1,
            4,
            4,
            4,
            480,
            480
          ]
        },
        {
          "bytes": 58982400,
          "dtype": "complex128",
          "shape": [
            64,
            60,
            2,
            480
          ]
        },
        {
          "bytes": 58982400,
          "dtype": "complex128",
          "shape": [
            64,
            60,
            2,
            480
          ]
        },
        {
          "bytes": 58982400,
          "dtype": "complex128",
          "shape": [
            64,
            2,
            480,
            60
          ]
        },
        {
          "bytes": 58982400,
          "dtype": "complex128",
          "shape": [
            64,
            2,
            480,
            60
          ]
        },
        {
          "bytes": 30720,
          "dtype": "float64",
          "shape": [
            64,
            60
          ]
        },
        {
          "bytes": 30720,
          "dtype": "float64",
          "shape": [
            64,
            60
          ]
        },
        {
          "bytes": 30720,
          "dtype": "float64",
          "shape": [
            64,
            60
          ]
        },
        {
          "bytes": 4096,
          "dtype": "float64",
          "shape": [
            64,
            8
          ]
        }
      ]
    },
    {
      "t": 6.618227591039613,
      "bytes_in_use": 0,
      "peak_bytes_in_use": 0,
      "live_bytes_sum": 774789468,
      "n_live_arrays": 21,
      "top_arrays": [
        {
          "bytes": 235929600,
          "dtype": "complex128",
          "shape": [
            64,
            480,
            480
          ]
        },
        {
          "bytes": 235929600,
          "dtype": "complex128",
          "shape": [
            1,
            1,
            1,
            4,
            4,
            4,
            480,
            480
          ]
        },
        {
          "bytes": 58982400,
          "dtype": "complex128",
          "shape": [
            64,
            60,
            2,
            480
          ]
        },
        {
          "bytes": 58982400,
          "dtype": "complex128",
          "shape": [
            64,
            60,
            2,
            480
          ]
        },
        {
          "bytes": 58982400,
          "dtype": "complex128",
          "shape": [
            64,
            2,
            480,
            60
          ]
        },
        {
          "bytes": 58982400,
          "dtype": "complex128",
          "shape": [
            64,
            2,
            480,
            60
          ]
        },
        {
          "bytes": 51118080,
          "dtype": "complex128",
          "shape": [
            64,
            52,
            2,
            480
          ]
        },
        {
          "bytes": 7864320,
          "dtype": "complex128",
          "shape": [
            64,
            8,
            2,
            480
          ]
        },
        {
          "bytes": 7864320,
          "dtype": "complex128",
          "shape": [
            64,
            2,
            480,
            8
          ]
        },
        {
          "bytes": 30720,
          "dtype": "float64",
          "shape": [
            64,
            60
          ]
        }
      ]
    },
    {
      "t": 6.8685650650877506,
      "bytes_in_use": 0,
      "peak_bytes_in_use": 0,
      "live_bytes_sum": 707942744,
      "n_live_arrays": 17,
      "top_arrays": [
        {
          "bytes": 235929600,
          "dtype": "complex128",
          "shape": [
            64,
            480,
            480
          ]
        },
        {
          "bytes": 235929600,
          "dtype": "complex128",
          "shape": [
            1,
            1,
            1,
            4,
            4,
            4,
            480,
            480
          ]
        },
        {
          "bytes": 58982400,
          "dtype": "complex128",
          "shape": [
            64,
            60,
            2,
            480
          ]
        },
        {
          "bytes": 58982400,
          "dtype": "complex128",
          "shape": [
            64,
            60,
            2,
            480
          ]
        },
        {
          "bytes": 58982400,
          "dtype": "complex128",
          "shape": [
            64,
            2,
            480,
            60
          ]
        },
        {
          "bytes": 58982400,
          "dtype": "complex128",
          "shape": [
            64,
            2,
            480,
            60
          ]
        },
        {
          "bytes": 30720,
          "dtype": "float64",
          "shape": [
            64,
            60
          ]
        },
        {
          "bytes": 30720,
          "dtype": "float64",
          "shape": [
            64,
            60
          ]
        },
        {
          "bytes": 30720,
          "dtype": "float64",
          "shape": [
            64,
            60
          ]
        },
        {
          "bytes": 26624,
          "dtype": "float64",
          "shape": [
            64,
            52
          ]
        }
      ]
    },
    {
      "t": 7.118869053199887,
      "bytes_in_use": 0,
      "peak_bytes_in_use": 0,
      "live_bytes_sum": 707942744,
      "n_live_arrays": 17,
      "top_arrays": [
        {
          "bytes": 235929600,
          "dtype": "complex128",
          "shape": [
            64,
            480,
            480
          ]
        },
        {
          "bytes": 235929600,
          "dtype": "complex128",
          "shape": [
            1,
            1,
            1,
            4,
            4,
            4,
            480,
            480
          ]
        },
        {
          "bytes": 58982400,
          "dtype": "complex128",
          "shape": [
            64,
            60,
            2,
            480
          ]
        },
        {
          "bytes": 58982400,
          "dtype": "complex128",
          "shape": [
            64,
            60,
            2,
            480
          ]
        },
        {
          "bytes": 58982400,
          "dtype": "complex128",
          "shape": [
            64,
            2,
            480,
            60
          ]
        },
        {
          "bytes": 58982400,
          "dtype": "complex128",
          "shape": [
            64,
            2,
            480,
            60
          ]
        },
        {
          "bytes": 30720,
          "dtype": "float64",
          "shape": [
            64,
            60
          ]
        },
        {
          "bytes": 30720,
          "dtype": "float64",
          "shape": [
            64,
            60
          ]
        },
        {
          "bytes": 30720,
          "dtype": "float64",
          "shape": [
            64,
            60
          ]
        },
        {
          "bytes": 26624,
          "dtype": "float64",
          "shape": [
            64,
            52
          ]
        }
      ]
    },
    {
      "t": 7.369475807994604,
      "bytes_in_use": 0,
      "peak_bytes_in_use": 0,
      "live_bytes_sum": 825938280,
      "n_live_arrays": 25,
      "top_arrays": [
        {
          "bytes": 235929600,
          "dtype": "complex128",
          "shape": [
            64,
            480,
            480
          ]
        },
        {
          "bytes": 235929600,
          "dtype": "complex128",
          "shape": [
            1,
            1,
            1,
            4,
            4,
            4,
            480,
            480
          ]
        },
        {
          "bytes": 58982400,
          "dtype": "complex128",
          "shape": [
            64,
            60,
            2,
            480
          ]
        },
        {
          "bytes": 58982400,
          "dtype": "complex128",
          "shape": [
            64,
            60,
            2,
            480
          ]
        },
        {
          "bytes": 58982400,
          "dtype": "complex128",
          "shape": [
            64,
            2,
            480,
            60
          ]
        },
        {
          "bytes": 58982400,
          "dtype": "complex128",
          "shape": [
            64,
            2,
            480,
            60
          ]
        },
        {
          "bytes": 51118080,
          "dtype": "complex128",
          "shape": [
            64,
            52,
            2,
            480
          ]
        },
        {
          "bytes": 51118080,
          "dtype": "complex128",
          "shape": [
            64,
            2,
            480,
            52
          ]
        },
        {
          "bytes": 7864320,
          "dtype": "complex128",
          "shape": [
            64,
            8,
            2,
            480
          ]
        },
        {
          "bytes": 7864320,
          "dtype": "complex128",
          "shape": [
            64,
            2,
            480,
            8
          ]
        }
      ]
    },
    {
      "t": 7.619733397150412,
      "bytes_in_use": 0,
      "peak_bytes_in_use": 0,
      "live_bytes_sum": 943810600,
      "n_live_arrays": 13,
      "top_arrays": [
        {
          "bytes": 235929600,
          "dtype": "complex128",
          "shape": [
            64,
            480,
            480
          ]
        },
        {
          "bytes": 235929600,
          "dtype": "complex128",
          "shape": [
            64,
            480,
            480
          ]
        },
        {
          "bytes": 235929600,
          "dtype": "complex128",
          "shape": [
            1,
            1,
            1,
            4,
            4,
            4,
            480,
            480
          ]
        },
        {
          "bytes": 58982400,
          "dtype": "complex128",
          "shape": [
            64,
            60,
            2,
            480
          ]
        },
        {
          "bytes": 58982400,
          "dtype": "complex128",
          "shape": [
            64,
            60,
            2,
            480
          ]
        },
        {
          "bytes": 58982400,
          "dtype": "complex128",
          "shape": [
            64,
            2,
            480,
            60
          ]
        },
        {
          "bytes": 58982400,
          "dtype": "complex128",
          "shape": [
            64,
            2,
            480,
            60
          ]
        },
        {
          "bytes": 30720,
          "dtype": "float64",
          "shape": [
            64,
            60
          ]
        },
        {
          "bytes": 30720,
          "dtype": "float64",
          "shape": [
            64,
            60
          ]
        },
        {
          "bytes": 30720,
          "dtype": "float64",
          "shape": [
            64,
            60
          ]
        }
      ]
    },
    {
      "t": 7.870125245070085,
      "bytes_in_use": 0,
      "peak_bytes_in_use": 0,
      "live_bytes_sum": 943810600,
      "n_live_arrays": 13,
      "top_arrays": [
        {
          "bytes": 235929600,
          "dtype": "complex128",
          "shape": [
            64,
            480,
            480
          ]
        },
        {
          "bytes": 235929600,
          "dtype": "complex128",
          "shape": [
            64,
            480,
            480
          ]
        },
        {
          "bytes": 235929600,
          "dtype": "complex128",
          "shape": [
            1,
            1,
            1,
            4,
            4,
            4,
            480,
            480
          ]
        },
        {
          "bytes": 58982400,
          "dtype": "complex128",
          "shape": [
            64,
            60,
            2,
            480
          ]
        },
        {
          "bytes": 58982400,
          "dtype": "complex128",
          "shape": [
            64,
            60,
            2,
            480
          ]
        },
        {
          "bytes": 58982400,
          "dtype": "complex128",
          "shape": [
            64,
            2,
            480,
            60
          ]
        },
        {
          "bytes": 58982400,
          "dtype": "complex128",
          "shape": [
            64,
            2,
            480,
            60
          ]
        },
        {
          "bytes": 30720,
          "dtype": "float64",
          "shape": [
            64,
            60
          ]
        },
        {
          "bytes": 30720,
          "dtype": "float64",
          "shape": [
            64,
            60
          ]
        },
        {
          "bytes": 30720,
          "dtype": "float64",
          "shape": [
            64,
            60
          ]
        }
      ]
    },
    {
      "t": 8.120405446970835,
      "bytes_in_use": 0,
      "peak_bytes_in_use": 0,
      "live_bytes_sum": 960430600,
      "n_live_arrays": 18,
      "top_arrays": [
        {
          "bytes": 235929600,
          "dtype": "complex128",
          "shape": [
            64,
            480,
            480
          ]
        },
        {
          "bytes": 235929600,
          "dtype": "complex128",
          "shape": [
            64,
            480,
            480
          ]
        },
        {
          "bytes": 235929600,
          "dtype": "complex128",
          "shape": [
            1,
            1,
            1,
            4,
            4,
            4,
            480,
            480
          ]
        },
        {
          "bytes": 58982400,
          "dtype": "complex128",
          "shape": [
            64,
            60,
            2,
            480
          ]
        },
        {
          "bytes": 58982400,
          "dtype": "complex128",
          "shape": [
            64,
            60,
            2,
            480
          ]
        },
        {
          "bytes": 58982400,
          "dtype": "complex128",
          "shape": [
            64,
            2,
            480,
            60
          ]
        },
        {
          "bytes": 58982400,
          "dtype": "complex128",
          "shape": [
            64,
            2,
            480,
            60
          ]
        },
        {
          "bytes": 11059200,
          "dtype": "complex128",
          "shape": [
            3,
            64,
            60,
            60
          ]
        },
        {
          "bytes": 3686400,
          "dtype": "complex128",
          "shape": [
            64,
            60,
            60
          ]
        },
        {
          "bytes": 1843200,
          "dtype": "float64",
          "shape": [
            64,
            60,
            60
          ]
        }
      ]
    },
    {
      "t": 8.371157302055508,
      "bytes_in_use": 0,
      "peak_bytes_in_use": 0,
      "live_bytes_sum": 960432028,
      "n_live_arrays": 24,
      "top_arrays": [
        {
          "bytes": 235929600,
          "dtype": "complex128",
          "shape": [
            64,
            480,
            480
          ]
        },
        {
          "bytes": 235929600,
          "dtype": "complex128",
          "shape": [
            64,
            480,
            480
          ]
        },
        {
          "bytes": 235929600,
          "dtype": "complex128",
          "shape": [
            1,
            1,
            1,
            4,
            4,
            4,
            480,
            480
          ]
        },
        {
          "bytes": 58982400,
          "dtype": "complex128",
          "shape": [
            64,
            60,
            2,
            480
          ]
        },
        {
          "bytes": 58982400,
          "dtype": "complex128",
          "shape": [
            64,
            60,
            2,
            480
          ]
        },
        {
          "bytes": 58982400,
          "dtype": "complex128",
          "shape": [
            64,
            2,
            480,
            60
          ]
        },
        {
          "bytes": 58982400,
          "dtype": "complex128",
          "shape": [
            64,
            2,
            480,
            60
          ]
        },
        {
          "bytes": 11059200,
          "dtype": "complex128",
          "shape": [
            3,
            64,
            60,
            60
          ]
        },
        {
          "bytes": 3686400,
          "dtype": "complex128",
          "shape": [
            64,
            60,
            60
          ]
        },
        {
          "bytes": 1843200,
          "dtype": "float64",
          "shape": [
            64,
            60,
            60
          ]
        }
      ]
    },
    {
      "t": 8.62191668106243,
      "bytes_in_use": 0,
      "peak_bytes_in_use": 0,
      "live_bytes_sum": 960445352,
      "n_live_arrays": 30,
      "top_arrays": [
        {
          "bytes": 235929600,
          "dtype": "complex128",
          "shape": [
            64,
            480,
            480
          ]
        },
        {
          "bytes": 235929600,
          "dtype": "complex128",
          "shape": [
            64,
            480,
            480
          ]
        },
        {
          "bytes": 235929600,
          "dtype": "complex128",
          "shape": [
            1,
            1,
            1,
            4,
            4,
            4,
            480,
            480
          ]
        },
        {
          "bytes": 58982400,
          "dtype": "complex128",
          "shape": [
            64,
            60,
            2,
            480
          ]
        },
        {
          "bytes": 58982400,
          "dtype": "complex128",
          "shape": [
            64,
            60,
            2,
            480
          ]
        },
        {
          "bytes": 58982400,
          "dtype": "complex128",
          "shape": [
            64,
            2,
            480,
            60
          ]
        },
        {
          "bytes": 58982400,
          "dtype": "complex128",
          "shape": [
            64,
            2,
            480,
            60
          ]
        },
        {
          "bytes": 11059200,
          "dtype": "complex128",
          "shape": [
            3,
            64,
            60,
            60
          ]
        },
        {
          "bytes": 3686400,
          "dtype": "complex128",
          "shape": [
            64,
            60,
            60
          ]
        },
        {
          "bytes": 1843200,
          "dtype": "float64",
          "shape": [
            64,
            60,
            60
          ]
        }
      ]
    },
    {
      "t": 8.872246399056166,
      "bytes_in_use": 0,
      "peak_bytes_in_use": 0,
      "live_bytes_sum": 961922096,
      "n_live_arrays": 24,
      "top_arrays": [
        {
          "bytes": 235929600,
          "dtype": "complex128",
          "shape": [
            64,
            480,
            480
          ]
        },
        {
          "bytes": 235929600,
          "dtype": "complex128",
          "shape": [
            64,
            480,
            480
          ]
        },
        {
          "bytes": 235929600,
          "dtype": "complex128",
          "shape": [
            1,
            1,
            1,
            4,
            4,
            4,
            480,
            480
          ]
        },
        {
          "bytes": 58982400,
          "dtype": "complex128",
          "shape": [
            64,
            60,
            2,
            480
          ]
        },
        {
          "bytes": 58982400,
          "dtype": "complex128",
          "shape": [
            64,
            60,
            2,
            480
          ]
        },
        {
          "bytes": 58982400,
          "dtype": "complex128",
          "shape": [
            64,
            2,
            480,
            60
          ]
        },
        {
          "bytes": 58982400,
          "dtype": "complex128",
          "shape": [
            64,
            2,
            480,
            60
          ]
        },
        {
          "bytes": 11059200,
          "dtype": "complex128",
          "shape": [
            3,
            64,
            60,
            60
          ]
        },
        {
          "bytes": 3686400,
          "dtype": "complex128",
          "shape": [
            64,
            60,
            60
          ]
        },
        {
          "bytes": 1843200,
          "dtype": "float64",
          "shape": [
            64,
            60,
            60
          ]
        }
      ]
    },
    {
      "t": 9.122698374092579,
      "bytes_in_use": 0,
      "peak_bytes_in_use": 0,
      "live_bytes_sum": 961926588,
      "n_live_arrays": 25,
      "top_arrays": [
        {
          "bytes": 235929600,
          "dtype": "complex128",
          "shape": [
            64,
            480,
            480
          ]
        },
        {
          "bytes": 235929600,
          "dtype": "complex128",
          "shape": [
            64,
            480,
            480
          ]
        },
        {
          "bytes": 235929600,
          "dtype": "complex128",
          "shape": [
            1,
            1,
            1,
            4,
            4,
            4,
            480,
            480
          ]
        },
        {
          "bytes": 58982400,
          "dtype": "complex128",
          "shape": [
            64,
            60,
            2,
            480
          ]
        },
        {
          "bytes": 58982400,
          "dtype": "complex128",
          "shape": [
            64,
            60,
            2,
            480
          ]
        },
        {
          "bytes": 58982400,
          "dtype": "complex128",
          "shape": [
            64,
            2,
            480,
            60
          ]
        },
        {
          "bytes": 58982400,
          "dtype": "complex128",
          "shape": [
            64,
            2,
            480,
            60
          ]
        },
        {
          "bytes": 11059200,
          "dtype": "complex128",
          "shape": [
            3,
            64,
            60,
            60
          ]
        },
        {
          "bytes": 3686400,
          "dtype": "complex128",
          "shape": [
            64,
            60,
            60
          ]
        },
        {
          "bytes": 1843200,
          "dtype": "float64",
          "shape": [
            64,
            60,
            60
          ]
        }
      ]
    },
    {
      "t": 9.373129228129983,
      "bytes_in_use": 0,
      "peak_bytes_in_use": 0,
      "live_bytes_sum": 962165768,
      "n_live_arrays": 27,
      "top_arrays": [
        {
          "bytes": 235929600,
          "dtype": "complex128",
          "shape": [
            64,
            480,
            480
          ]
        },
        {
          "bytes": 235929600,
          "dtype": "complex128",
          "shape": [
            64,
            480,
            480
          ]
        },
        {
          "bytes": 235929600,
          "dtype": "complex128",
          "shape": [
            1,
            1,
            1,
            4,
            4,
            4,
            480,
            480
          ]
        },
        {
          "bytes": 58982400,
          "dtype": "complex128",
          "shape": [
            64,
            60,
            2,
            480
          ]
        },
        {
          "bytes": 58982400,
          "dtype": "complex128",
          "shape": [
            64,
            60,
            2,
            480
          ]
        },
        {
          "bytes": 58982400,
          "dtype": "complex128",
          "shape": [
            64,
            2,
            480,
            60
          ]
        },
        {
          "bytes": 58982400,
          "dtype": "complex128",
          "shape": [
            64,
            2,
            480,
            60
          ]
        },
        {
          "bytes": 11059200,
          "dtype": "complex128",
          "shape": [
            3,
            64,
            60,
            60
          ]
        },
        {
          "bytes": 3686400,
          "dtype": "complex128",
          "shape": [
            64,
            60,
            60
          ]
        },
        {
          "bytes": 1843200,
          "dtype": "float64",
          "shape": [
            64,
            60,
            60
          ]
        }
      ]
    },
    {
      "t": 9.623566654976457,
      "bytes_in_use": 0,
      "peak_bytes_in_use": 0,
      "live_bytes_sum": 962804744,
      "n_live_arrays": 29,
      "top_arrays": [
        {
          "bytes": 235929600,
          "dtype": "complex128",
          "shape": [
            64,
            480,
            480
          ]
        },
        {
          "bytes": 235929600,
          "dtype": "complex128",
          "shape": [
            64,
            480,
            480
          ]
        },
        {
          "bytes": 235929600,
          "dtype": "complex128",
          "shape": [
            1,
            1,
            1,
            4,
            4,
            4,
            480,
            480
          ]
        },
        {
          "bytes": 58982400,
          "dtype": "complex128",
          "shape": [
            64,
            60,
            2,
            480
          ]
        },
        {
          "bytes": 58982400,
          "dtype": "complex128",
          "shape": [
            64,
            60,
            2,
            480
          ]
        },
        {
          "bytes": 58982400,
          "dtype": "complex128",
          "shape": [
            64,
            2,
            480,
            60
          ]
        },
        {
          "bytes": 58982400,
          "dtype": "complex128",
          "shape": [
            64,
            2,
            480,
            60
          ]
        },
        {
          "bytes": 11059200,
          "dtype": "complex128",
          "shape": [
            3,
            64,
            60,
            60
          ]
        },
        {
          "bytes": 3686400,
          "dtype": "complex128",
          "shape": [
            64,
            60,
            60
          ]
        },
        {
          "bytes": 1843200,
          "dtype": "float64",
          "shape": [
            64,
            60,
            60
          ]
        }
      ]
    },
    {
      "t": 9.874047165038064,
      "bytes_in_use": 0,
      "peak_bytes_in_use": 0,
      "live_bytes_sum": 964295688,
      "n_live_arrays": 30,
      "top_arrays": [
        {
          "bytes": 235929600,
          "dtype": "complex128",
          "shape": [
            64,
            480,
            480
          ]
        },
        {
          "bytes": 235929600,
          "dtype": "complex128",
          "shape": [
            64,
            480,
            480
          ]
        },
        {
          "bytes": 235929600,
          "dtype": "complex128",
          "shape": [
            1,
            1,
            1,
            4,
            4,
            4,
            480,
            480
          ]
        },
        {
          "bytes": 58982400,
          "dtype": "complex128",
          "shape": [
            64,
            60,
            2,
            480
          ]
        },
        {
          "bytes": 58982400,
          "dtype": "complex128",
          "shape": [
            64,
            60,
            2,
            480
          ]
        },
        {
          "bytes": 58982400,
          "dtype": "complex128",
          "shape": [
            64,
            2,
            480,
            60
          ]
        },
        {
          "bytes": 58982400,
          "dtype": "complex128",
          "shape": [
            64,
            2,
            480,
            60
          ]
        },
        {
          "bytes": 11059200,
          "dtype": "complex128",
          "shape": [
            3,
            64,
            60,
            60
          ]
        },
        {
          "bytes": 3686400,
          "dtype": "complex128",
          "shape": [
            64,
            60,
            60
          ]
        },
        {
          "bytes": 1843200,
          "dtype": "float64",
          "shape": [
            64,
            60,
            60
          ]
        }
      ]
    },
    {
      "t": 10.124524979153648,
      "bytes_in_use": 0,
      "peak_bytes_in_use": 0,
      "live_bytes_sum": 960430560,
      "n_live_arrays": 23,
      "top_arrays": [
        {
          "bytes": 235929600,
          "dtype": "complex128",
          "shape": [
            64,
            480,
            480
          ]
        },
        {
          "bytes": 235929600,
          "dtype": "complex128",
          "shape": [
            64,
            480,
            480
          ]
        },
        {
          "bytes": 235929600,
          "dtype": "complex128",
          "shape": [
            1,
            1,
            1,
            4,
            4,
            4,
            480,
            480
          ]
        },
        {
          "bytes": 58982400,
          "dtype": "complex128",
          "shape": [
            64,
            60,
            2,
            480
          ]
        },
        {
          "bytes": 58982400,
          "dtype": "complex128",
          "shape": [
            64,
            60,
            2,
            480
          ]
        },
        {
          "bytes": 58982400,
          "dtype": "complex128",
          "shape": [
            64,
            2,
            480,
            60
          ]
        },
        {
          "bytes": 58982400,
          "dtype": "complex128",
          "shape": [
            64,
            2,
            480,
            60
          ]
        },
        {
          "bytes": 11059200,
          "dtype": "complex128",
          "shape": [
            3,
            64,
            60,
            60
          ]
        },
        {
          "bytes": 3686400,
          "dtype": "complex128",
          "shape": [
            64,
            60,
            60
          ]
        },
        {
          "bytes": 1843200,
          "dtype": "float64",
          "shape": [
            64,
            60,
            60
          ]
        }
      ]
    },
    {
      "t": 10.380147211020812,
      "bytes_in_use": 0,
      "peak_bytes_in_use": 0,
      "live_bytes_sum": 960430416,
      "n_live_arrays": 21,
      "top_arrays": [
        {
          "bytes": 235929600,
          "dtype": "complex128",
          "shape": [
            64,
            480,
            480
          ]
        },
        {
          "bytes": 235929600,
          "dtype": "complex128",
          "shape": [
            64,
            480,
            480
          ]
        },
        {
          "bytes": 235929600,
          "dtype": "complex128",
          "shape": [
            1,
            1,
            1,
            4,
            4,
            4,
            480,
            480
          ]
        },
        {
          "bytes": 58982400,
          "dtype": "complex128",
          "shape": [
            64,
            60,
            2,
            480
          ]
        },
        {
          "bytes": 58982400,
          "dtype": "complex128",
          "shape": [
            64,
            60,
            2,
            480
          ]
        },
        {
          "bytes": 58982400,
          "dtype": "complex128",
          "shape": [
            64,
            2,
            480,
            60
          ]
        },
        {
          "bytes": 58982400,
          "dtype": "complex128",
          "shape": [
            64,
            2,
            480,
            60
          ]
        },
        {
          "bytes": 11059200,
          "dtype": "complex128",
          "shape": [
            3,
            64,
            60,
            60
          ]
        },
        {
          "bytes": 3686400,
          "dtype": "complex128",
          "shape": [
            64,
            60,
            60
          ]
        },
        {
          "bytes": 1843200,
          "dtype": "float64",
          "shape": [
            64,
            60,
            60
          ]
        }
      ]
    },
    {
      "t": 10.631072340998799,
      "bytes_in_use": 0,
      "peak_bytes_in_use": 0,
      "live_bytes_sum": 973013400,
      "n_live_arrays": 24,
      "top_arrays": [
        {
          "bytes": 235929600,
          "dtype": "complex128",
          "shape": [
            64,
            480,
            480
          ]
        },
        {
          "bytes": 235929600,
          "dtype": "complex128",
          "shape": [
            64,
            480,
            480
          ]
        },
        {
          "bytes": 235929600,
          "dtype": "complex128",
          "shape": [
            1,
            1,
            1,
            4,
            4,
            4,
            480,
            480
          ]
        },
        {
          "bytes": 58982400,
          "dtype": "complex128",
          "shape": [
            64,
            60,
            2,
            480
          ]
        },
        {
          "bytes": 58982400,
          "dtype": "complex128",
          "shape": [
            64,
            60,
            2,
            480
          ]
        },
        {
          "bytes": 58982400,
          "dtype": "complex128",
          "shape": [
            64,
            2,
            480,
            60
          ]
        },
        {
          "bytes": 58982400,
          "dtype": "complex128",
          "shape": [
            64,
            2,
            480,
            60
          ]
        },
        {
          "bytes": 11059200,
          "dtype": "complex128",
          "shape": [
            3,
            64,
            60,
            60
          ]
        },
        {
          "bytes": 6291456,
          "dtype": "float64",
          "shape": [
            262144,
            3
          ]
        },
        {
          "bytes": 6291456,
          "dtype": "float64",
          "shape": [
            3,
            262144
          ]
        }
      ]
    },
    {
      "t": 10.881466103019193,
      "bytes_in_use": 0,
      "peak_bytes_in_use": 0,
      "live_bytes_sum": 973014000,
      "n_live_arrays": 25,
      "top_arrays": [
        {
          "bytes": 235929600,
          "dtype": "complex128",
          "shape": [
            64,
            480,
            480
          ]
        },
        {
          "bytes": 235929600,
          "dtype": "complex128",
          "shape": [
            64,
            480,
            480
          ]
        },
        {
          "bytes": 235929600,
          "dtype": "complex128",
          "shape": [
            1,
            1,
            1,
            4,
            4,
            4,
            480,
            480
          ]
        },
        {
          "bytes": 58982400,
          "dtype": "complex128",
          "shape": [
            64,
            60,
            2,
            480
          ]
        },
        {
          "bytes": 58982400,
          "dtype": "complex128",
          "shape": [
            64,
            60,
            2,
            480
          ]
        },
        {
          "bytes": 58982400,
          "dtype": "complex128",
          "shape": [
            64,
            2,
            480,
            60
          ]
        },
        {
          "bytes": 58982400,
          "dtype": "complex128",
          "shape": [
            64,
            2,
            480,
            60
          ]
        },
        {
          "bytes": 11059200,
          "dtype": "complex128",
          "shape": [
            3,
            64,
            60,
            60
          ]
        },
        {
          "bytes": 6291456,
          "dtype": "float64",
          "shape": [
            262144,
            3
          ]
        },
        {
          "bytes": 6291456,
          "dtype": "float64",
          "shape": [
            262144,
            3
          ]
        }
      ]
    },
    {
      "t": 11.131953516975045,
      "bytes_in_use": 0,
      "peak_bytes_in_use": 0,
      "live_bytes_sum": 1201604216,
      "n_live_arrays": 29,
      "top_arrays": [
        {
          "bytes": 235929600,
          "dtype": "complex128",
          "shape": [
            64,
            480,
            480
          ]
        },
        {
          "bytes": 235929600,
          "dtype": "complex128",
          "shape": [
            64,
            480,
            480
          ]
        },
        {
          "bytes": 235929600,
          "dtype": "complex128",
          "shape": [
            1,
            1,
            1,
            4,
            4,
            4,
            480,
            480
          ]
        },
        {
          "bytes": 169869312,
          "dtype": "float64",
          "shape": [
            262144,
            27,
            3
          ]
        },
        {
          "bytes": 58982400,
          "dtype": "complex128",
          "shape": [
            64,
            60,
            2,
            480
          ]
        },
        {
          "bytes": 58982400,
          "dtype": "complex128",
          "shape": [
            64,
            60,
            2,
            480
          ]
        },
        {
          "bytes": 58982400,
          "dtype": "complex128",
          "shape": [
            64,
            2,
            480,
            60
          ]
        },
        {
          "bytes": 58982400,
          "dtype": "complex128",
          "shape": [
            64,
            2,
            480,
            60
          ]
        },
        {
          "bytes": 56623104,
          "dtype": "float64",
          "shape": [
            262144,
            27
          ]
        },
        {
          "bytes": 11059200,
          "dtype": "complex128",
          "shape": [
            3,
            64,
            60,
            60
          ]
        }
      ]
    },
    {
      "t": 11.382440860150382,
      "bytes_in_use": 0,
      "peak_bytes_in_use": 0,
      "live_bytes_sum": 1207895672,
      "n_live_arrays": 30,
      "top_arrays": [
        {
          "bytes": 235929600,
          "dtype": "complex128",
          "shape": [
            64,
            480,
            480
          ]
        },
        {
          "bytes": 235929600,
          "dtype": "complex128",
          "shape": [
            64,
            480,
            480
          ]
        },
        {
          "bytes": 235929600,
          "dtype": "complex128",
          "shape": [
            1,
            1,
            1,
            4,
            4,
            4,
            480,
            480
          ]
        },
        {
          "bytes": 169869312,
          "dtype": "float64",
          "shape": [
            262144,
            27,
            3
          ]
        },
        {
          "bytes": 58982400,
          "dtype": "complex128",
          "shape": [
            64,
            60,
            2,
            480
          ]
        },
        {
          "bytes": 58982400,
          "dtype": "complex128",
          "shape": [
            64,
            60,
            2,
            480
          ]
        },
        {
          "bytes": 58982400,
          "dtype": "complex128",
          "shape": [
            64,
            2,
            480,
            60
          ]
        },
        {
          "bytes": 58982400,
          "dtype": "complex128",
          "shape": [
            64,
            2,
            480,
            60
          ]
        },
        {
          "bytes": 56623104,
          "dtype": "float64",
          "shape": [
            262144,
            27
          ]
        },
        {
          "bytes": 11059200,
          "dtype": "complex128",
          "shape": [
            3,
            64,
            60,
            60
          ]
        }
      ]
    },
    {
      "t": 11.6328482280951,
      "bytes_in_use": 0,
      "peak_bytes_in_use": 0,
      "live_bytes_sum": 989790552,
      "n_live_arrays": 28,
      "top_arrays": [
        {
          "bytes": 235929600,
          "dtype": "complex128",
          "shape": [
            64,
            480,
            480
          ]
        },
        {
          "bytes": 235929600,
          "dtype": "complex128",
          "shape": [
            64,
            480,
            480
          ]
        },
        {
          "bytes": 235929600,
          "dtype": "complex128",
          "shape": [
            1,
            1,
            1,
            4,
            4,
            4,
            480,
            480
          ]
        },
        {
          "bytes": 58982400,
          "dtype": "complex128",
          "shape": [
            64,
            60,
            2,
            480
          ]
        },
        {
          "bytes": 58982400,
          "dtype": "complex128",
          "shape": [
            64,
            60,
            2,
            480
          ]
        },
        {
          "bytes": 58982400,
          "dtype": "complex128",
          "shape": [
            64,
            2,
            480,
            60
          ]
        },
        {
          "bytes": 58982400,
          "dtype": "complex128",
          "shape": [
            64,
            2,
            480,
            60
          ]
        },
        {
          "bytes": 11059200,
          "dtype": "complex128",
          "shape": [
            3,
            64,
            60,
            60
          ]
        },
        {
          "bytes": 6291456,
          "dtype": "float64",
          "shape": [
            262144,
            3
          ]
        },
        {
          "bytes": 6291456,
          "dtype": "float64",
          "shape": [
            262144,
            3
          ]
        }
      ]
    },
    {
      "t": 11.883391620125622,
      "bytes_in_use": 0,
      "peak_bytes_in_use": 0,
      "live_bytes_sum": 1002373464,
      "n_live_arrays": 31,
      "top_arrays": [
        {
          "bytes": 235929600,
          "dtype": "complex128",
          "shape": [
            64,
            480,
            480
          ]
        },
        {
          "bytes": 235929600,
          "dtype": "complex128",
          "shape": [
            64,
            480,
            480
          ]
        },
        {
          "bytes": 235929600,
          "dtype": "complex128",
          "shape": [
            1,
            1,
            1,
            4,
            4,
            4,
            480,
            480
          ]
        },
        {
          "bytes": 58982400,
          "dtype": "complex128",
          "shape": [
            64,
            60,
            2,
            480
          ]
        },
        {
          "bytes": 58982400,
          "dtype": "complex128",
          "shape": [
            64,
            60,
            2,
            480
          ]
        },
        {
          "bytes": 58982400,
          "dtype": "complex128",
          "shape": [
            64,
            2,
            480,
            60
          ]
        },
        {
          "bytes": 58982400,
          "dtype": "complex128",
          "shape": [
            64,
            2,
            480,
            60
          ]
        },
        {
          "bytes": 11059200,
          "dtype": "complex128",
          "shape": [
            3,
            64,
            60,
            60
          ]
        },
        {
          "bytes": 6291456,
          "dtype": "float64",
          "shape": [
            262144,
            3
          ]
        },
        {
          "bytes": 6291456,
          "dtype": "float64",
          "shape": [
            262144,
            3
          ]
        }
      ]
    },
    {
      "t": 12.133870146004483,
      "bytes_in_use": 0,
      "peak_bytes_in_use": 0,
      "live_bytes_sum": 998179304,
      "n_live_arrays": 42,
      "top_arrays": [
        {
          "bytes": 235929600,
          "dtype": "complex128",
          "shape": [
            64,
            480,
            480
          ]
        },
        {
          "bytes": 235929600,
          "dtype": "complex128",
          "shape": [
            64,
            480,
            480
          ]
        },
        {
          "bytes": 235929600,
          "dtype": "complex128",
          "shape": [
            1,
            1,
            1,
            4,
            4,
            4,
            480,
            480
          ]
        },
        {
          "bytes": 58982400,
          "dtype": "complex128",
          "shape": [
            64,
            60,
            2,
            480
          ]
        },
        {
          "bytes": 58982400,
          "dtype": "complex128",
          "shape": [
            64,
            60,
            2,
            480
          ]
        },
        {
          "bytes": 58982400,
          "dtype": "complex128",
          "shape": [
            64,
            2,
            480,
            60
          ]
        },
        {
          "bytes": 58982400,
          "dtype": "complex128",
          "shape": [
            64,
            2,
            480,
            60
          ]
        },
        {
          "bytes": 11059200,
          "dtype": "complex128",
          "shape": [
            3,
            64,
            60,
            60
          ]
        },
        {
          "bytes": 6291456,
          "dtype": "float64",
          "shape": [
            262144,
            3
          ]
        },
        {
          "bytes": 6291456,
          "dtype": "float64",
          "shape": [
            262144,
            3
          ]
        }
      ]
    },
    {
      "t": 12.384340767050162,
      "bytes_in_use": 0,
      "peak_bytes_in_use": 0,
      "live_bytes_sum": 998179560,
      "n_live_arrays": 51,
      "top_arrays": [
        {
          "bytes": 235929600,
          "dtype": "complex128",
          "shape": [
            64,
            480,
            480
          ]
        },
        {
          "bytes": 235929600,
          "dtype": "complex128",
          "shape": [
            64,
            480,
            480
          ]
        },
        {
          "bytes": 235929600,
          "dtype": "complex128",
          "shape": [
            1,
            1,
            1,
            4,
            4,
            4,
            480,
            480
          ]
        },
        {
          "bytes": 58982400,
          "dtype": "complex128",
          "shape": [
            64,
            60,
            2,
            480
          ]
        },
        {
          "bytes": 58982400,
          "dtype": "complex128",
          "shape": [
            64,
            60,
            2,
            480
          ]
        },
        {
          "bytes": 58982400,
          "dtype": "complex128",
          "shape": [
            64,
            2,
            480,
            60
          ]
        },
        {
          "bytes": 58982400,
          "dtype": "complex128",
          "shape": [
            64,
            2,
            480,
            60
          ]
        },
        {
          "bytes": 11059200,
          "dtype": "complex128",
          "shape": [
            3,
            64,
            60,
            60
          ]
        },
        {
          "bytes": 6291456,
          "dtype": "float64",
          "shape": [
            262144,
            3
          ]
        },
        {
          "bytes": 6291456,
          "dtype": "float64",
          "shape": [
            262144,
            3
          ]
        }
      ]
    },
    {
      "t": 12.634699792135507,
      "bytes_in_use": 0,
      "peak_bytes_in_use": 0,
      "live_bytes_sum": 947498984,
      "n_live_arrays": 20,
      "top_arrays": [
        {
          "bytes": 235929600,
          "dtype": "complex128",
          "shape": [
            64,
            480,
            480
          ]
        },
        {
          "bytes": 235929600,
          "dtype": "complex128",
          "shape": [
            64,
            480,
            480
          ]
        },
        {
          "bytes": 235929600,
          "dtype": "complex128",
          "shape": [
            1,
            1,
            1,
            4,
            4,
            4,
            480,
            480
          ]
        },
        {
          "bytes": 58982400,
          "dtype": "complex128",
          "shape": [
            64,
            60,
            2,
            480
          ]
        },
        {
          "bytes": 58982400,
          "dtype": "complex128",
          "shape": [
            64,
            60,
            2,
            480
          ]
        },
        {
          "bytes": 58982400,
          "dtype": "complex128",
          "shape": [
            64,
            2,
            480,
            60
          ]
        },
        {
          "bytes": 58982400,
          "dtype": "complex128",
          "shape": [
            64,
            2,
            480,
            60
          ]
        },
        {
          "bytes": 3686400,
          "dtype": "complex128",
          "shape": [
            64,
            60,
            60
          ]
        },
        {
          "bytes": 30720,
          "dtype": "float64",
          "shape": [
            64,
            60
          ]
        },
        {
          "bytes": 30720,
          "dtype": "float64",
          "shape": [
            64,
            60
          ]
        }
      ]
    },
    {
      "t": 12.885566468117759,
      "bytes_in_use": 0,
      "peak_bytes_in_use": 0,
      "live_bytes_sum": 947504680,
      "n_live_arrays": 23,
      "top_arrays": [
        {
          "bytes": 235929600,
          "dtype": "complex128",
          "shape": [
            64,
            480,
            480
          ]
        },
        {
          "bytes": 235929600,
          "dtype": "complex128",
          "shape": [
            64,
            480,
            480
          ]
        },
        {
          "bytes": 235929600,
          "dtype": "complex128",
          "shape": [
            1,
            1,
            1,
            4,
            4,
            4,
            480,
            480
          ]
        },
        {
          "bytes": 58982400,
          "dtype": "complex128",
          "shape": [
            64,
            60,
            2,
            480
          ]
        },
        {
          "bytes": 58982400,
          "dtype": "complex128",
          "shape": [
            64,
            60,
            2,
            480
          ]
        },
        {
          "bytes": 58982400,
          "dtype": "complex128",
          "shape": [
            64,
            2,
            480,
            60
          ]
        },
        {
          "bytes": 58982400,
          "dtype": "complex128",
          "shape": [
            64,
            2,
            480,
            60
          ]
        },
        {
          "bytes": 3686400,
          "dtype": "complex128",
          "shape": [
            64,
            60,
            60
          ]
        },
        {
          "bytes": 30720,
          "dtype": "float64",
          "shape": [
            64,
            60
          ]
        },
        {
          "bytes": 30720,
          "dtype": "float64",
          "shape": [
            64,
            60
          ]
        }
      ]
    },
    {
      "t": 13.136041718069464,
      "bytes_in_use": 0,
      "peak_bytes_in_use": 0,
      "live_bytes_sum": 947504680,
      "n_live_arrays": 23,
      "top_arrays": [
        {
          "bytes": 235929600,
          "dtype": "complex128",
          "shape": [
            64,
            480,
            480
          ]
        },
        {
          "bytes": 235929600,
          "dtype": "complex128",
          "shape": [
            64,
            480,
            480
          ]
        },
        {
          "bytes": 235929600,
          "dtype": "complex128",
          "shape": [
            1,
            1,
            1,
            4,
            4,
            4,
            480,
            480
          ]
        },
        {
          "bytes": 58982400,
          "dtype": "complex128",
          "shape": [
            64,
            60,
            2,
            480
          ]
        },
        {
          "bytes": 58982400,
          "dtype": "complex128",
          "shape": [
            64,
            60,
            2,
            480
          ]
        },
        {
          "bytes": 58982400,
          "dtype": "complex128",
          "shape": [
            64,
            2,
            480,
            60
          ]
        },
        {
          "bytes": 58982400,
          "dtype": "complex128",
          "shape": [
            64,
            2,
            480,
            60
          ]
        },
        {
          "bytes": 3686400,
          "dtype": "complex128",
          "shape": [
            64,
            60,
            60
          ]
        },
        {
          "bytes": 30720,
          "dtype": "float64",
          "shape": [
            64,
            60
          ]
        },
        {
          "bytes": 30720,
          "dtype": "float64",
          "shape": [
            64,
            60
          ]
        }
      ]
    },
    {
      "t": 13.388210752978921,
      "bytes_in_use": 0,
      "peak_bytes_in_use": 0,
      "live_bytes_sum": 951191080,
      "n_live_arrays": 24,
      "top_arrays": [
        {
          "bytes": 235929600,
          "dtype": "complex128",
          "shape": [
            64,
            480,
            480
          ]
        },
        {
          "bytes": 235929600,
          "dtype": "complex128",
          "shape": [
            64,
            480,
            480
          ]
        },
        {
          "bytes": 235929600,
          "dtype": "complex128",
          "shape": [
            1,
            1,
            1,
            4,
            4,
            4,
            480,
            480
          ]
        },
        {
          "bytes": 58982400,
          "dtype": "complex128",
          "shape": [
            64,
            60,
            2,
            480
          ]
        },
        {
          "bytes": 58982400,
          "dtype": "complex128",
          "shape": [
            64,
            60,
            2,
            480
          ]
        },
        {
          "bytes": 58982400,
          "dtype": "complex128",
          "shape": [
            64,
            2,
            480,
            60
          ]
        },
        {
          "bytes": 58982400,
          "dtype": "complex128",
          "shape": [
            64,
            2,
            480,
            60
          ]
        },
        {
          "bytes": 3686400,
          "dtype": "complex128",
          "shape": [
            64,
            60,
            60
          ]
        },
        {
          "bytes": 3686400,
          "dtype": "complex128",
          "shape": [
            64,
            60,
            60
          ]
        },
        {
          "bytes": 30720,
          "dtype": "float64",
          "shape": [
            64,
            60
          ]
        }
      ]
    },
    {
      "t": 13.638665533158928,
      "bytes_in_use": 0,
      "peak_bytes_in_use": 0,
      "live_bytes_sum": 951191080,
      "n_live_arrays": 24,
      "top_arrays": [
        {
          "bytes": 235929600,
          "dtype": "complex128",
          "shape": [
            64,
            480,
            480
          ]
        },
        {
          "bytes": 235929600,
          "dtype": "complex128",
          "shape": [
            64,
            480,
            480
          ]
        },
        {
          "bytes": 235929600,
          "dtype": "complex128",
          "shape": [
            1,
            1,
            1,
            4,
            4,
            4,
            480,
            480
          ]
        },
        {
          "bytes": 58982400,
          "dtype": "complex128",
          "shape": [
            64,
            60,
            2,
            480
          ]
        },
        {
          "bytes": 58982400,
          "dtype": "complex128",
          "shape": [
            64,
            60,
            2,
            480
          ]
        },
        {
          "bytes": 58982400,
          "dtype": "complex128",
          "shape": [
            64,
            2,
            480,
            60
          ]
        },
        {
          "bytes": 58982400,
          "dtype": "complex128",
          "shape": [
            64,
            2,
            480,
            60
          ]
        },
        {
          "bytes": 3686400,
          "dtype": "complex128",
          "shape": [
            64,
            60,
            60
          ]
        },
        {
          "bytes": 3686400,
          "dtype": "complex128",
          "shape": [
            64,
            60,
            60
          ]
        },
        {
          "bytes": 30720,
          "dtype": "float64",
          "shape": [
            64,
            60
          ]
        }
      ]
    },
    {
      "t": 13.889157297089696,
      "bytes_in_use": 0,
      "peak_bytes_in_use": 0,
      "live_bytes_sum": 954877480,
      "n_live_arrays": 25,
      "top_arrays": [
        {
          "bytes": 235929600,
          "dtype": "complex128",
          "shape": [
            64,
            480,
            480
          ]
        },
        {
          "bytes": 235929600,
          "dtype": "complex128",
          "shape": [
            64,
            480,
            480
          ]
        },
        {
          "bytes": 235929600,
          "dtype": "complex128",
          "shape": [
            1,
            1,
            1,
            4,
            4,
            4,
            480,
            480
          ]
        },
        {
          "bytes": 58982400,
          "dtype": "complex128",
          "shape": [
            64,
            60,
            2,
            480
          ]
        },
        {
          "bytes": 58982400,
          "dtype": "complex128",
          "shape": [
            64,
            60,
            2,
            480
          ]
        },
        {
          "bytes": 58982400,
          "dtype": "complex128",
          "shape": [
            64,
            2,
            480,
            60
          ]
        },
        {
          "bytes": 58982400,
          "dtype": "complex128",
          "shape": [
            64,
            2,
            480,
            60
          ]
        },
        {
          "bytes": 3686400,
          "dtype": "complex128",
          "shape": [
            64,
            60,
            60
          ]
        },
        {
          "bytes": 3686400,
          "dtype": "complex128",
          "shape": [
            64,
            60,
            60
          ]
        },
        {
          "bytes": 3686400,
          "dtype": "complex128",
          "shape": [
            64,
            60,
            60
          ]
        }
      ]
    },
    {
      "t": 14.139567112084478,
      "bytes_in_use": 0,
      "peak_bytes_in_use": 0,
      "live_bytes_sum": 958650288,
      "n_live_arrays": 30,
      "top_arrays": [
        {
          "bytes": 235929600,
          "dtype": "complex128",
          "shape": [
            64,
            480,
            480
          ]
        },
        {
          "bytes": 235929600,
          "dtype": "complex128",
          "shape": [
            64,
            480,
            480
          ]
        },
        {
          "bytes": 235929600,
          "dtype": "complex128",
          "shape": [
            1,
            1,
            1,
            4,
            4,
            4,
            480,
            480
          ]
        },
        {
          "bytes": 58982400,
          "dtype": "complex128",
          "shape": [
            64,
            60,
            2,
            480
          ]
        },
        {
          "bytes": 58982400,
          "dtype": "complex128",
          "shape": [
            64,
            60,
            2,
            480
          ]
        },
        {
          "bytes": 58982400,
          "dtype": "complex128",
          "shape": [
            64,
            2,
            480,
            60
          ]
        },
        {
          "bytes": 58982400,
          "dtype": "complex128",
          "shape": [
            64,
            2,
            480,
            60
          ]
        },
        {
          "bytes": 3686400,
          "dtype": "complex128",
          "shape": [
            64,
            60,
            60
          ]
        },
        {
          "bytes": 3686400,
          "dtype": "complex128",
          "shape": [
            64,
            60,
            60
          ]
        },
        {
          "bytes": 3686400,
          "dtype": "complex128",
          "shape": [
            64,
            60,
            60
          ]
        }
      ]
    },
    {
      "t": 14.389964444097131,
      "bytes_in_use": 0,
      "peak_bytes_in_use": 0,
      "live_bytes_sum": 958563880,
      "n_live_arrays": 26,
      "top_arrays": [
        {
          "bytes": 235929600,
          "dtype": "complex128",
          "shape": [
            64,
            480,
            480
          ]
        },
        {
          "bytes": 235929600,
          "dtype": "complex128",
          "shape": [
            64,
            480,
            480
          ]
        },
        {
          "bytes": 235929600,
          "dtype": "complex128",
          "shape": [
            1,
            1,
            1,
            4,
            4,
            4,
            480,
            480
          ]
        },
        {
          "bytes": 58982400,
          "dtype": "complex128",
          "shape": [
            64,
            60,
            2,
            480
          ]
        },
        {
          "bytes": 58982400,
          "dtype": "complex128",
          "shape": [
            64,
            60,
            2,
            480
          ]
        },
        {
          "bytes": 58982400,
          "dtype": "complex128",
          "shape": [
            64,
            2,
            480,
            60
          ]
        },
        {
          "bytes": 58982400,
          "dtype": "complex128",
          "shape": [
            64,
            2,
            480,
            60
          ]
        },
        {
          "bytes": 3686400,
          "dtype": "complex128",
          "shape": [
            64,
            60,
            60
          ]
        },
        {
          "bytes": 3686400,
          "dtype": "complex128",
          "shape": [
            64,
            60,
            60
          ]
        },
        {
          "bytes": 3686400,
          "dtype": "complex128",
          "shape": [
            64,
            60,
            60
          ]
        }
      ]
    },
    {
      "t": 14.640383786987513,
      "bytes_in_use": 0,
      "peak_bytes_in_use": 0,
      "live_bytes_sum": 958563880,
      "n_live_arrays": 26,
      "top_arrays": [
        {
          "bytes": 235929600,
          "dtype": "complex128",
          "shape": [
            64,
            480,
            480
          ]
        },
        {
          "bytes": 235929600,
          "dtype": "complex128",
          "shape": [
            64,
            480,
            480
          ]
        },
        {
          "bytes": 235929600,
          "dtype": "complex128",
          "shape": [
            1,
            1,
            1,
            4,
            4,
            4,
            480,
            480
          ]
        },
        {
          "bytes": 58982400,
          "dtype": "complex128",
          "shape": [
            64,
            60,
            2,
            480
          ]
        },
        {
          "bytes": 58982400,
          "dtype": "complex128",
          "shape": [
            64,
            60,
            2,
            480
          ]
        },
        {
          "bytes": 58982400,
          "dtype": "complex128",
          "shape": [
            64,
            2,
            480,
            60
          ]
        },
        {
          "bytes": 58982400,
          "dtype": "complex128",
          "shape": [
            64,
            2,
            480,
            60
          ]
        },
        {
          "bytes": 3686400,
          "dtype": "complex128",
          "shape": [
            64,
            60,
            60
          ]
        },
        {
          "bytes": 3686400,
          "dtype": "complex128",
          "shape": [
            64,
            60,
            60
          ]
        },
        {
          "bytes": 3686400,
          "dtype": "complex128",
          "shape": [
            64,
            60,
            60
          ]
        }
      ]
    },
    {
      "t": 14.890780327143148,
      "bytes_in_use": 0,
      "peak_bytes_in_use": 0,
      "live_bytes_sum": 962307888,
      "n_live_arrays": 30,
      "top_arrays": [
        {
          "bytes": 235929600,
          "dtype": "complex128",
          "shape": [
            64,
            480,
            480
          ]
        },
        {
          "bytes": 235929600,
          "dtype": "complex128",
          "shape": [
            64,
            480,
            480
          ]
        },
        {
          "bytes": 235929600,
          "dtype": "complex128",
          "shape": [
            1,
            1,
            1,
            4,
            4,
            4,
            480,
            480
          ]
        },
        {
          "bytes": 58982400,
          "dtype": "complex128",
          "shape": [
            64,
            60,
            2,
            480
          ]
        },
        {
          "bytes": 58982400,
          "dtype": "complex128",
          "shape": [
            64,
            60,
            2,
            480
          ]
        },
        {
          "bytes": 58982400,
          "dtype": "complex128",
          "shape": [
            64,
            2,
            480,
            60
          ]
        },
        {
          "bytes": 58982400,
          "dtype": "complex128",
          "shape": [
            64,
            2,
            480,
            60
          ]
        },
        {
          "bytes": 3686400,
          "dtype": "complex128",
          "shape": [
            64,
            60,
            60
          ]
        },
        {
          "bytes": 3686400,
          "dtype": "complex128",
          "shape": [
            64,
            60,
            60
          ]
        },
        {
          "bytes": 3686400,
          "dtype": "complex128",
          "shape": [
            64,
            60,
            60
          ]
        }
      ]
    },
    {
      "t": 15.141159163089469,
      "bytes_in_use": 0,
      "peak_bytes_in_use": 0,
      "live_bytes_sum": 976995880,
      "n_live_arrays": 31,
      "top_arrays": [
        {
          "bytes": 235929600,
          "dtype": "complex128",
          "shape": [
            64,
            480,
            480
          ]
        },
        {
          "bytes": 235929600,
          "dtype": "complex128",
          "shape": [
            64,
            480,
            480
          ]
        },
        {
          "bytes": 235929600,
          "dtype": "complex128",
          "shape": [
            1,
            1,
            1,
            4,
            4,
            4,
            480,
            480
          ]
        },
        {
          "bytes": 58982400,
          "dtype": "complex128",
          "shape": [
            64,
            60,
            2,
            480
          ]
        },
        {
          "bytes": 58982400,
          "dtype": "complex128",
          "shape": [
            64,
            60,
            2,
            480
          ]
        },
        {
          "bytes": 58982400,
          "dtype": "complex128",
          "shape": [
            64,
            2,
            480,
            60
          ]
        },
        {
          "bytes": 58982400,
          "dtype": "complex128",
          "shape": [
            64,
            2,
            480,
            60
          ]
        },
        {
          "bytes": 3686400,
          "dtype": "complex128",
          "shape": [
            64,
            60,
            60
          ]
        },
        {
          "bytes": 3686400,
          "dtype": "complex128",
          "shape": [
            64,
            60,
            60
          ]
        },
        {
          "bytes": 3686400,
          "dtype": "complex128",
          "shape": [
            64,
            60,
            60
          ]
        }
      ]
    },
    {
      "t": 15.39156923815608,
      "bytes_in_use": 0,
      "peak_bytes_in_use": 0,
      "live_bytes_sum": 976995880,
      "n_live_arrays": 31,
      "top_arrays": [
        {
          "bytes": 235929600,
          "dtype": "complex128",
          "shape": [
            64,
            480,
            480
          ]
        },
        {
          "bytes": 235929600,
          "dtype": "complex128",
          "shape": [
            64,
            480,
            480
          ]
        },
        {
          "bytes": 235929600,
          "dtype": "complex128",
          "shape": [
            1,
            1,
            1,
            4,
            4,
            4,
            480,
            480
          ]
        },
        {
          "bytes": 58982400,
          "dtype": "complex128",
          "shape": [
            64,
            60,
            2,
            480
          ]
        },
        {
          "bytes": 58982400,
          "dtype": "complex128",
          "shape": [
            64,
            60,
            2,
            480
          ]
        },
        {
          "bytes": 58982400,
          "dtype": "complex128",
          "shape": [
            64,
            2,
            480,
            60
          ]
        },
        {
          "bytes": 58982400,
          "dtype": "complex128",
          "shape": [
            64,
            2,
            480,
            60
          ]
        },
        {
          "bytes": 3686400,
          "dtype": "complex128",
          "shape": [
            64,
            60,
            60
          ]
        },
        {
          "bytes": 3686400,
          "dtype": "complex128",
          "shape": [
            64,
            60,
            60
          ]
        },
        {
          "bytes": 3686400,
          "dtype": "complex128",
          "shape": [
            64,
            60,
            60
          ]
        }
      ]
    },
    {
      "t": 15.625303203007206,
      "bytes_in_use": 0,
      "peak_bytes_in_use": 0,
      "live_bytes_sum": 16,
      "n_live_arrays": 2,
      "top_arrays": [
        {
          "bytes": 8,
          "dtype": "float64",
          "shape": []
        },
        {
          "bytes": 8,
          "dtype": "float64",
          "shape": []
        }
      ]
    }
  ]
}